whiptail/__init__.py
whiptail/py.typed
whiptail_dialogs-0.4.1.dist-info/LICENSE
whiptail_dialogs-0.4.1.dist-info/METADATA
whiptail_dialogs-0.4.1.dist-info/WHEEL
whiptail_dialogs-0.4.1.dist-info/entry_points.txt
whiptail_dialogs-0.4.1.dist-info/RECORD
