Metadata-Version: 2.2
Name: whiptail-dialogs
Version: 0.4.1
Summary: Use whiptail to display dialog boxes from Python scripts.
Author-email: Dominic Davis-Foster <dominic@davis-foster.co.uk>
License: BSD-3-Clause
Keywords: console,dialog,utility,whiptail
Home-page: https://github.com/domdfcoding/whiptail
Project-URL: Issue Tracker, https://github.com/domdfcoding/whiptail/issues
Project-URL: Source Code, https://github.com/domdfcoding/whiptail
Project-URL: Documentation, https://whiptail.readthedocs.io/en/latest
Platform: Windows
Platform: macOS
Platform: Linux
Classifier: Development Status :: 5 - Production/Stable
Classifier: Environment :: Console
Classifier: Intended Audience :: Developers
Classifier: License :: OSI Approved :: BSD License
Classifier: Operating System :: OS Independent
Classifier: Programming Language :: Python
Classifier: Programming Language :: Python :: 3 :: Only
Classifier: Programming Language :: Python :: 3.7
Classifier: Programming Language :: Python :: 3.8
Classifier: Programming Language :: Python :: 3.9
Classifier: Programming Language :: Python :: 3.10
Classifier: Programming Language :: Python :: 3.11
Classifier: Programming Language :: Python :: 3.12
Classifier: Programming Language :: Python :: Implementation :: CPython
Classifier: Topic :: Software Development :: Libraries :: Python Modules
Classifier: Typing :: Typed
Requires-Python: >=3.7
Requires-Dist: domdf-python-tools>=1.7.0
Requires-Dist: typing-extensions>=4.1.1
